pyfibers/__init__.py
pyfibers/compile.py
pyfibers/fiber.py
pyfibers/model_enum.py
pyfibers/stimulation.py
pyfibers/MOD/AXNODE_myel.mod
pyfibers/MOD/BK.mod
pyfibers/MOD/CaPump.mod
pyfibers/MOD/CaV12.mod
pyfibers/MOD/CaV22.mod
pyfibers/MOD/DNav18.mod
pyfibers/MOD/HCN.mod
pyfibers/MOD/KA14.mod
pyfibers/MOD/KA34.mod
pyfibers/MOD/KM.mod
pyfibers/MOD/KV21.mod
pyfibers/MOD/NaCX.mod
pyfibers/MOD/NaCaPump.mod
pyfibers/MOD/NaV7.mod
pyfibers/MOD/NaV9.mod
pyfibers/MOD/Nakpump.mod
pyfibers/MOD/NakpumpSchild.mod
pyfibers/MOD/RattayAberham.mod
pyfibers/MOD/SK.mod
pyfibers/MOD/caextscale.mod
pyfibers/MOD/caintscale.mod
pyfibers/MOD/can.mod
pyfibers/MOD/cat.mod
pyfibers/MOD/extrapump.mod
pyfibers/MOD/h.mod
pyfibers/MOD/k_ion_dynamics.mod
pyfibers/MOD/k_ion_dynamics_tigerholm.mod
pyfibers/MOD/ka.mod
pyfibers/MOD/kca.mod
pyfibers/MOD/kd.mod
pyfibers/MOD/kdr.mod
pyfibers/MOD/kdrTiger.mod
pyfibers/MOD/kds.mod
pyfibers/MOD/kf.mod
pyfibers/MOD/kna.mod
pyfibers/MOD/ks.mod
pyfibers/MOD/leak.mod
pyfibers/MOD/leakSchild.mod
pyfibers/MOD/na_ion_dynamics.mod
pyfibers/MOD/na_ion_dynamics_tigerholm.mod
pyfibers/MOD/naf.mod
pyfibers/MOD/naf97mean.mod
pyfibers/MOD/nahh.mod
pyfibers/MOD/nas.mod
pyfibers/MOD/nas97mean.mod
pyfibers/MOD/nattxs.mod
pyfibers/MOD/nav1p9.mod
pyfibers/MOD/newNaV8.mod
pyfibers/MOD/sweeney.mod
pyfibers/MOD/train.mod
pyfibers/models/__init__.py
pyfibers/models/mrg.py
pyfibers/models/rattay.py
pyfibers/models/schild.py
pyfibers/models/sundt.py
pyfibers/models/sweeney.py
pyfibers/models/thio.py
pyfibers/models/tigerholm.py
pyfibers-0.8.3.dist-info/entry_points.txt
pyfibers-0.8.3.dist-info/licenses/LICENSE
pyfibers-0.8.3.dist-info/WHEEL
pyfibers-0.8.3.dist-info/METADATA
pyfibers-0.8.3.dist-info/RECORD
