Metadata-Version: 2.4
Name: pyfibers
Version: 0.8.3
Summary: Modeling stimulation of peripheral nerve fibers
Keywords: stimulation,modeling,computational,fibers,peripheral nerve
Author: Daniel Marshall, Elie Farah, Eric Musselman, Nicole Pelot, Warren Grill
Requires-Python: >=3.10
Classifier: Development Status :: 3 - Alpha
Classifier: Programming Language :: Python :: 3.10
Classifier: Programming Language :: Python :: 3.11
Classifier: Programming Language :: Python :: 3.12
Classifier: Programming Language :: Python :: 3.13
Classifier: Operating System :: OS Independent
License-File: LICENSE
Requires-Dist: matplotlib==3.10.*
Requires-Dist: multiprocess==0.*
Requires-Dist: numpy==2.2.*
Requires-Dist: pandas==2.2.*
Requires-Dist: scipy==1.15.*
Requires-Dist: seaborn==0.13.*
Requires-Dist: nd_line==0.2.*
Requires-Dist: aenum==3.1.*
Requires-Dist: mock==5.* ; extra == "dev"
Requires-Dist: pre-commit==4.0.* ; extra == "dev"
Requires-Dist: pytest==8.* ; extra == "dev"
Requires-Dist: pytest-cov==6.* ; extra == "dev"
Requires-Dist: pytest-sugar==1.* ; extra == "dev"
Requires-Dist: sphinx==7.* ; extra == "dev"
Requires-Dist: sphinx-rtd-theme==3.* ; extra == "dev"
Requires-Dist: sphinx-copybutton==0.5.* ; extra == "dev"
Requires-Dist: IPython==8.* ; extra == "dev"
Requires-Dist: enum-tools[sphinx]==0.12.* ; extra == "dev"
Requires-Dist: sphinxcontrib-bibtex==2.6.* ; extra == "dev"
Requires-Dist: moviepy==2.1.* ; extra == "dev"
Requires-Dist: sphinx_autodoc_typehints==2.3.* ; extra == "dev"
Requires-Dist: piccolo-theme==0.24.* ; extra == "dev"
Requires-Dist: myst-nb==1.2.* ; extra == "dev"
Project-URL: Changelog, https://github.com/wmglab-duke/pyfibers/blob/main/CHANGELOG.md
Project-URL: Documentation, https://wmglab-duke.github.io/pyfibers/
Project-URL: Homepage, https://github.com/wmglab-duke/pyfibers
Project-URL: Issues, https://github.com/wmglab-duke/pyfibers/issues
Project-URL: Repository, https://github.com/wmglab-duke/pyfibers
Provides-Extra: dev
